Metadata-Version: 2.1
Name: Devkek
Version: 0.999999999
Summary: What
Author: D
Author-email: nasr2python@gmail.com
Classifier: Programming Language :: Python :: 3
Classifier: License :: OSI Approved :: MIT License
Classifier: Operating System :: OS Independent
